icecube_voka-0.1.6.dist-info/licenses/LICENSE
voka/__init__.py
voka/compare.py
voka/histogram.py
voka/lof.py
voka/metrics.py
voka/model.py
voka/py.typed
voka/two_sample.py
voka/tools/__init__.py
voka/tools/render.py
icecube_voka-0.1.6.dist-info/METADATA
icecube_voka-0.1.6.dist-info/WHEEL
icecube_voka-0.1.6.dist-info/top_level.txt
icecube_voka-0.1.6.dist-info/RECORD
