Metadata-Version: 2.4
Name: icecube-voka
Version: 0.1.6
Summary: Sanity checks on sequences/histograms using ML techniques. 
Author-email: IceCube <developers@icecube.wisc.edu>
License-Expression: MIT
Project-URL: Homepage, https://pypi.org/project/icecube-voka/
Project-URL: Tracker, https://github.com/icecube/voka/issues
Project-URL: Source, https://github.com/icecube/voka
Keywords: IceCube,WIPAC,histogram comparison,outlier detection,statistical tests,empirical p-value threshold,poissonian statistics
Classifier: Programming Language :: Python :: 3.9
Classifier: Programming Language :: Python :: 3.10
Classifier: Programming Language :: Python :: 3.11
Classifier: Programming Language :: Python :: 3.12
Classifier: Programming Language :: Python :: 3.13
Classifier: Programming Language :: Python :: 3.14
Requires-Python: <3.15,>=3.9
License-File: LICENSE
Requires-Dist: numpy
Requires-Dist: scipy
Provides-Extra: tests
Requires-Dist: pytest; extra == "tests"
Provides-Extra: mypy
Requires-Dist: pytest; extra == "mypy"
Dynamic: license-file
